<?xml version="1.0" encoding="utf-8"?>
<!--Copyright Nucletron © 2010
-->
<part xmlns:xsi="http://www.w3.org/2001/XMLSchema-instance" xmlns:xsd="http://www.w3.org/2001/XMLSchema" revision="1">
  <information partid="110231-50" type="Tube">
    <description>
      <longDescription>Needle 50 mm</longDescription>
      <shortDescription>length={0}mm</shortDescription>
      <parameter>50</parameter>
    </description>
  </information>
  <centerCurve tipLength="6">
    <point x="54.51" y="0" z="316.5" />
    <point x="54.08" y="0" z="314.04" />
    <point x="53.64" y="0" z="311.57" />
    <point x="53.21" y="0" z="309.11" />
    <point x="52.77" y="0" z="306.65" />
    <point x="52.34" y="0" z="304.19" />
    <point x="51.9" y="0" z="301.72" />
    <point x="51.47" y="0" z="299.26" />
    <point x="51.03" y="0" z="296.8" />
    <point x="50.6" y="0" z="294.34" />
    <point x="50.16" y="0" z="291.87" />
    <point x="49.73" y="0" z="289.41" />
    <point x="49.29" y="0" z="286.95" />
    <point x="48.86" y="0" z="284.49" />
    <point x="48.42" y="0" z="282.02" />
    <point x="47.99" y="0" z="279.56" />
    <point x="47.55" y="0" z="277.1" />
    <point x="47.12" y="0" z="274.64" />
    <point x="46.68" y="0" z="272.17" />
    <point x="46.25" y="0" z="269.71" />
    <point x="45.81" y="0" z="267.25" />
    <point x="45.38" y="0" z="264.79" />
    <point x="44.94" y="0" z="262.32" />
    <point x="44.51" y="0" z="259.86" />
    <point x="44.07" y="0" z="257.4" />
    <point x="43.64" y="0" z="254.94" />
    <point x="43.2" y="0" z="252.47" />
    <point x="42.77" y="0" z="250.01" />
    <point x="42.33" y="0" z="247.55" />
    <marker1 x="53.64" y="0" z="311.57" />
  </centerCurve>
  <lumen diameter="2.5" />
  <anchorPoints>
    <point x="53.64" y="0.00" z="311.57" name="1st marker" />
  </anchorPoints>
  <connectors>
    <connector name="NEEDLE1">
      <centerPoint x="45.98" y="0" z="268.23" />
      <axisDirection x="0" y="1" z="0" />
      <referenceDirection x="0" y="0" z="1" />
    </connector>
    <connector name="NEEDLE2">
      <centerPoint x="45.98" y="0" z="268.23" />
      <axisDirection x="0" y="1" z="0" />
      <referenceDirection x="0" y="0" z="1" />
    </connector>
    <connector name="NEEDLE3">
      <centerPoint x="45.98" y="0" z="268.23" />
      <axisDirection x="0" y="1" z="0" />
      <referenceDirection x="0" y="0" z="1" />
    </connector>
    <connector name="NEEDLE4">
      <centerPoint x="45.98" y="0" z="268.23" />
      <axisDirection x="0" y="1" z="0" />
      <referenceDirection x="0" y="0" z="1" />
    </connector>
    <connector name="NEEDLE5">
      <centerPoint x="45.98" y="0" z="268.23" />
      <axisDirection x="0" y="1" z="0" />
      <referenceDirection x="0" y="0" z="1" />
    </connector>
    <connector name="NEEDLE6">
      <centerPoint x="45.98" y="0" z="268.23" />
      <axisDirection x="0" y="1" z="0" />
      <referenceDirection x="0" y="0" z="1" />
    </connector>
  </connectors>
  <skin>
    <triangles>
      <segment name="Step_0">
        <positions>54.03\-0.95\315.56\54.28\-1\315.52\54.52\-0.98\315.48\54.76\-0.9\315.43\54.97\-0.77\315.4\55.31\-0.13\315.34\55.31\0.13\315.34\55.13\0.59\315.37\54.03\0.95\315.56\54.68\0\317.48\53.35\0\315.68\53.38\0.25\315.68\52.49\0.37\310.42\52.61\0.59\310.4\47.63\0.68\273.36\47.44\0.84\273.4\47.22\0.95\273.44\47.9\1\278.74\49.27\0.9\289.32\51.68\0.59\305.14\51.56\0.37\305.16\53.47\0.48\315.66\50.44\0.98\294.54\49.07\0.95\283.94\48.56\0.68\278.62\46.78\0.59\268.1\53.62\0.68\315.64\53.8\0.84\315.6\52.78\0.77\310.37\52.99\0.9\310.34\50.23\0.84\289.15\46.9\0.37\268.08\47.78\0.48\273.34\47.87\0.25\273.32\52.29\0.98\305.03\52.54\1\304.99\51.86\0.95\299.7\51.16\0.84\294.41\49.49\0.68\283.87\50.42\0.68\289.12\46.96\-0.13\268.07\53.22\0.98\310.29\54.28\1\315.52\51.34\0.68\294.38\50.56\0.48\289.09\48.83\0\278.57\47.9\0\273.32\46.9\-0.37\268.08\47.87\-0.25\273.32\53.47\1\310.25\53.71\0.95\310.21\52.08\0.84\299.66\48.8\-0.25\278.58\54.52\0.98\315.48\54.76\0.9\315.43\53.01\0.84\304.91\49.72\-0.25\283.83\47.78\-0.48\273.34\46.78\-0.59\268.1\54.97\0.77\315.4\53.2\0.68\304.87\51.61\0\294.33\50.68\0\289.07\50.65\-0.25\289.08\48.56\-0.68\278.62\46.62\-0.77\268.13\47.63\-0.68\273.36\47.44\-0.84\273.4\54.28\0.48\310.11\55.25\0.37\315.35\53.43\0.25\304.83\53.46\0\304.83\51.58\-0.25\294.34\49.3\-0.84\283.9\47.22\-0.95\273.44\46.17\-0.98\268.21\46.97\-1\273.48\45.93\-1\268.25\54.39\0\310.09\51.34\-0.68\294.38\47.9\-1\278.74\46.73\-0.98\273.52\54.36\-0.25\310.09\52.42\-0.48\299.6\52.27\-0.68\299.63\50\-0.95\289.19\49.07\-0.95\283.94\48.83\-1\283.99\46.49\-0.9\273.56\52.08\-0.84\299.66\48.58\-0.98\284.03\55.25\-0.37\315.35\54.28\-0.48\310.11\51.86\-0.95\299.7\49.76\-1\289.24\49.51\-0.98\289.28\47.21\-0.77\278.86\45.27\-0.68\268.37\55.13\-0.59\315.37\49.27\-0.9\289.32\48.35\-0.9\284.07\48.14\-0.77\284.11\46.12\-0.59\273.63\45.03\-0.25\268.41\52.78\-0.95\304.95\47.04\-0.59\278.89\46.93\-0.37\278.91\45.94\-0.13\273.66\51.37\-0.98\299.79\50.2\-0.9\294.58\50\-0.77\294.62\45.94\0.13\273.66\50.92\-0.77\299.86\48.9\-0.59\289.39\48.78\-0.37\289.41\46\0.37\273.65\45.12\0.48\268.39\53.22\-0.98\310.29\49.83\-0.59\294.65\51.68\-0.59\305.14\47.79\0.13\284.17\47.04\0.59\278.89\46.28\0.77\273.6\53.8\-0.84\315.6\53.62\-0.68\315.64\52.78\-0.77\310.37\49.65\-0.13\294.68\47.21\0.77\278.86\46.49\0.9\273.56\52.61\-0.59\310.4\50.58\0.13\299.93\48.78\0.37\289.41\47.42\0.9\278.82\53.47\-0.48\315.66\53.38\-0.25\315.68\51.5\-0.13\305.17\51.5\0.13\305.17\48.9\0.59\289.39\47.65\0.98\278.78\46.73\0.98\273.52\46.17\0.98\268.21\45.93\1\268.25\46.97\1\273.48\49.83\0.59\294.65\50.75\0.59\299.89\50\0.77\294.62\48.35\0.9\284.07\48.58\0.98\284.03\52.54\0\299.58\51.58\0.25\294.34\52.51\-0.25\299.58\50.65\0.25\289.08\49.75\0\283.82\52.43\0.13\310.43\50.64\0.37\299.91\49.65\0.13\294.68\50.58\-0.13\299.93\49.71\0.37\294.67\48.72\0.13\289.42\46.87\0.13\278.92\46.93\0.37\278.91\46.87\-0.13\278.92\47.79\-0.13\284.17\49.71\-0.37\294.67\48.72\-0.13\289.42\52.49\-0.37\310.42\52.43\-0.13\310.43\47.97\0.59\284.14\47.85\0.37\284.16\46.12\0.59\273.63\48.14\0.77\284.11\51.13\0.9\299.83\50.2\0.9\294.58\50.92\0.77\299.86\52.06\0.9\305.08\51.85\0.77\305.11\49.07\0.77\289.36\51.61\1\299.74\51.37\0.98\299.79\49.51\0.98\289.28\49.76\1\289.24\52.78\0.95\304.95\50.93\0.95\294.45\50\0.95\289.19\50.68\1\294.49\48.15\0.95\278.69\48.83\1\283.99\53.94\0.84\310.17\48.37\0.84\278.65\52.27\0.68\299.63\49.3\0.84\283.9\54.13\0.68\310.13\53.35\0.48\304.85\52.42\0.48\299.6\51.49\0.48\294.35\48.71\0.48\278.6\54.36\0.25\310.09\52.51\0.25\299.58\49.72\0.25\283.83\48.8\0.25\278.58\49.64\0.48\283.84\53.43\-0.25\304.83\51.49\-0.48\294.35\50.56\-0.48\289.09\48.71\-0.48\278.6\53.2\-0.68\304.87\53.35\-0.48\304.85\50.42\-0.68\289.12\49.64\-0.48\283.84\53.94\-0.84\310.17\54.13\-0.68\310.13\51.16\-0.84\294.41\50.23\-0.84\289.15\49.49\-0.68\283.87\53.71\-0.95\310.21\53.01\-0.84\304.91\50.93\-0.95\294.45\48.15\-0.95\278.69\48.37\-0.84\278.65\53.47\-1\310.25\52.54\-1\304.99\51.61\-1\299.74\50.68\-1\294.49\52.29\-0.98\305.03\50.44\-0.98\294.54\47.65\-0.98\278.78\52.99\-0.9\310.34\52.06\-0.9\305.08\51.85\-0.77\305.11\51.13\-0.9\299.83\49.07\-0.77\289.36\46.28\-0.77\273.6\47.42\-0.9\278.82\51.56\-0.37\305.16\50.64\-0.37\299.91\50.75\-0.59\299.89\47.85\-0.37\284.16\47.97\-0.59\284.14\46\-0.37\273.65\46.96\0.13\268.07\45.03\0.25\268.41\45.27\0.68\268.37\45.45\0.84\268.33\45.68\0.95\268.29\46.41\0.9\268.17\46.62\0.77\268.13\45\0\268.41\45.68\-0.95\268.29\45.12\-0.48\268.39\45.45\-0.84\268.33\46.41\-0.9\268.17</positions>
	      <indices>134\9\10\134\133\9\133\124\9\124\123\9\123\0\9\2\9\1\2\3\9\3\4\9\4\98\9\98\91\9\91\5\9\5\6\9\6\69\9\69\7\9\7\59\9\59\54\9\54\53\9\53\42\9\42\8\9\8\27\9\21\9\26\21\11\9\11\10\9\1\9\0\26\9\27\11\153\10\11\12\153\11\21\12\12\21\13\19\13\175\173\175\171\172\171\22\179\22\180\186\180\23\185\23\188\15\188\14\245\14\25\245\15\14\245\244\15\15\244\16\185\16\17\186\17\147\179\147\18\172\18\145\173\145\144\19\144\20\12\20\153\12\19\20\12\13\19\21\26\13\13\26\28\175\28\174\171\174\178\22\178\184\180\184\183\23\183\190\188\190\24\14\24\32\25\32\31\25\14\32\26\27\28\28\27\29\174\29\34\178\34\177\184\177\182\183\182\30\190\30\38\24\38\195\32\195\33\31\33\239\31\32\33\27\8\29\29\8\41\34\41\35\177\35\36\182\36\37\30\37\39\38\39\200\195\200\199\33\199\46\239\46\40\239\33\46\8\42\41\41\42\49\35\49\181\36\181\51\37\51\43\39\43\44\200\44\198\199\198\45\46\45\48\40\48\47\40\46\48\42\53\49\49\53\50\181\50\55\51\55\189\43\189\194\44\194\151\198\151\152\45\152\52\48\52\57\47\57\58\47\48\57\53\54\50\50\54\187\55\187\60\189\60\193\194\193\149\151\149\62\152\62\56\52\56\204\57\204\66\58\66\65\58\57\66\54\59\187\187\59\191\60\191\192\193\192\197\149\197\61\62\61\63\56\63\208\204\208\64\66\64\67\65\67\250\65\66\67\59\7\191\191\7\68\192\68\70\197\70\148\61\148\72\63\72\203\208\203\213\64\213\218\67\218\74\250\74\75\250\67\74\7\69\68\68\69\196\70\196\71\148\71\150\72\150\202\203\202\207\213\207\73\218\73\217\74\217\76\75\76\77\75\74\76\69\6\196\196\6\78\71\78\201\150\201\83\202\83\79\207\79\212\73\212\86\217\86\80\76\80\81\77\81\247\77\76\81\6\5\78\78\5\82\201\82\206\83\206\84\79\84\211\212\211\85\86\85\87\80\87\225\81\225\88\247\88\249\247\81\88\5\91\82\82\91\92\206\92\205\84\205\89\211\89\216\85\216\94\87\94\90\225\90\232\88\232\231\249\231\97\249\88\231\91\98\92\92\98\210\205\210\215\89\215\93\216\93\222\94\222\95\90\95\100\232\100\96\231\96\102\97\102\248\97\231\102\98\4\210\210\4\209\215\209\104\93\104\221\222\221\224\95\224\99\100\99\101\96\101\105\102\105\238\248\238\103\248\102\238\4\3\209\209\3\214\104\214\220\221\220\108\224\108\109\99\109\230\101\230\237\105\237\106\238\106\107\103\107\246\103\238\107\3\2\214\214\2\219\220\219\223\108\223\229\109\229\110\230\110\113\237\113\236\106\236\161\107\161\111\246\111\240\246\107\111\2\1\219\219\1\117\223\117\227\229\227\112\110\112\118\113\118\114\236\114\162\161\162\159\111\159\115\240\115\116\240\111\115\1\0\117\117\0\226\227\226\228\112\228\235\118\235\163\114\163\164\162\164\120\159\120\160\115\160\169\116\169\241\116\115\169\0\123\226\226\123\125\228\125\119\235\119\234\163\234\126\164\126\158\120\158\168\160\168\121\169\121\122\241\122\242\241\169\122\123\124\125\125\124\129\119\129\233\234\233\156\126\156\155\158\155\131\168\131\167\121\167\127\122\127\128\242\128\243\242\122\128\124\133\129\129\133\165\233\165\135\156\135\130\155\130\157\131\157\137\167\137\170\127\170\132\128\132\139\243\139\141\243\128\139\133\134\165\165\134\166\135\166\136\130\136\154\157\154\143\137\143\176\170\176\146\132\146\138\139\138\142\141\142\140\141\139\142\134\10\166\166\10\153\136\153\20\154\20\144\143\144\145\176\145\18\146\18\147\138\147\17\142\17\16\140\16\244\140\142\16\78\71\196\71\148\70\82\201\78\148\61\197\201\150\71\61\62\149\150\72\148\62\152\151\72\63\61\152\45\198\63\56\62\45\46\199\56\52\152\52\48\45\153\136\166\136\130\135\154\136\20\130\155\156\157\130\154\155\158\126\131\155\157\158\120\164\168\158\131\120\159\162\160\120\168\159\111\161\115\159\160\106\161\107\236\162\161\114\164\162\163\126\164\234\156\126\233\135\156\165\166\135\143\154\144\137\157\143\167\131\137\121\168\167\169\160\121\173\144\19\175\173\19\28\175\13\176\143\145\170\137\176\127\167\170\122\121\127\29\174\28\172\145\173\171\172\173\174\171\175\146\176\18\132\170\146\128\127\132\41\34\29\34\178\174\179\18\172\22\179\172\178\22\171\138\146\147\139\132\138\49\35\41\35\177\34\177\184\178\186\147\179\180\186\179\184\180\22\142\138\17\50\181\49\181\36\35\36\182\177\182\183\184\185\17\186\23\185\186\183\23\180\187\55\50\55\51\181\51\37\36\37\30\182\30\190\183\15\16\185\188\15\185\190\188\23\191\60\187\60\189\55\189\43\51\43\39\37\39\38\30\38\24\190\24\14\188\68\192\191\192\193\60\193\194\189\194\44\43\44\200\39\200\195\38\195\32\24\196\70\68\70\197\192\197\149\193\149\151\194\151\198\44\198\199\200\199\33\195\92\206\82\206\83\201\83\202\150\202\203\72\203\208\63\208\204\56\204\57\52\210\205\92\205\84\206\84\79\83\79\207\202\207\213\203\213\64\208\64\66\204\209\215\210\215\89\205\89\211\84\211\212\79\212\73\207\73\218\213\218\67\64\214\104\209\104\93\215\93\216\89\216\85\211\85\86\212\86\217\73\217\74\218\219\220\214\220\221\104\221\222\93\222\94\216\94\87\85\87\80\86\80\76\217\117\223\219\223\108\220\108\224\221\224\95\222\95\90\94\90\225\87\225\81\80\226\227\117\227\229\223\229\109\108\109\99\224\99\100\95\100\232\90\232\88\225\125\228\226\228\112\227\112\110\229\110\230\109\230\101\99\101\96\100\96\231\232\129\119\125\119\235\228\235\118\112\118\113\110\113\237\230\237\105\101\105\102\96\165\233\129\233\234\119\234\163\235\163\114\118\114\236\113\236\106\237\106\238\105\240\239\246\240\31\239\240\116\31\31\116\25\25\116\241\245\241\242\244\242\243\140\243\141\140\244\243\25\241\245\245\242\244\239\40\246\246\40\103\103\40\47\248\47\58\97\58\65\249\65\250\247\250\75\77\247\75\103\47\248\248\58\97\97\65\249\249\250\247</indices>
      </segment>
    </triangles>
  </skin>
</part>